{
  "protocol": "h1a_assignment_carrier_audit_v1",
  "status_before_run": "frozen_not_run",
  "scope": "zero-training qualification of the H0 occupational carrier records for an exact count-constrained assignment Gate",
  "source": {
    "dataset": "qualified H0-E-v4 O1 occupational occurrence census",
    "manifest_sha256": "5080228b3452601a9d72c34a8cc4e8f26c51c11584a2c082c33662459029294a",
    "results_sha256": "baf1a293171f05a8866546cebf62cacc4d92bb35d661cf0df9f5d4f7911c94c1",
    "independent_audit_sha256": "bb2ea88de8fc2dba55a7cab55fdbc6d3992b5810f7f6b1c2a69a009642328961",
    "auditor_sha256": "b9045301dfdbcbded41ef3452167d9504baa51fc18252d19d150ea12db44a92c"
  },
  "scientific_contract": {
    "composition_role": "C is a sampled upstream variable; observed C may be used only in the oracle-C conditional qualification and must be labelled as such",
    "site_assignment_role": "target-only output used in quotient NLL and accuracy, never an input feature",
    "parent_action_role": "species-free carrier symmetry and quotient measure",
    "child_space_group_role": "target-derived audit metadata and prohibited model input",
    "occupation_class_role": "target-derived reconstruction label and prohibited model input",
    "fixed_cif_row_accuracy": "diagnostic only"
  },
  "acceptance": {
    "candidate_carriers": 454,
    "candidate_carriers_by_split": {
      "test": 53,
      "train": 358,
      "val": 43
    },
    "maximum_atoms": 20,
    "maximum_species": 7,
    "maximum_dynamic_program_states": 100000,
    "uniform_target_quotient_probability_median_max": 0.5,
    "occupational_symmetry_breaking_fraction_min": 0.1,
    "material_split_disjoint": true
  },
  "decision_rule": {
    "pass": "freeze a separately versioned oracle-C assignment Q1 using only species-free carrier features and exact parent-action quotient NLL",
    "fail": "repair the carrier/data interface only; do not train assignment, L1, or M1",
    "boundary": "This audit cannot pass assignment Q1, L1, M1, free joint H1a, tensor/oracle work, relaxation, DFT, or DFPT."
  }
}
